adafruit_icm20x.py
adafruit_circuitpython_icm20x-2.1.8.dist-info/licenses/LICENSE
adafruit_circuitpython_icm20x-2.1.8.dist-info/METADATA
adafruit_circuitpython_icm20x-2.1.8.dist-info/WHEEL
adafruit_circuitpython_icm20x-2.1.8.dist-info/top_level.txt
adafruit_circuitpython_icm20x-2.1.8.dist-info/RECORD
