Metadata-Version: 2.4
Name: adafruit-circuitpython-icm20x
Version: 2.1.8
Summary: Library for the ST ICM-20X Wide-Range 6-DoF Accelerometer and Gyro Family
Author-email: Adafruit Industries <circuitpython@adafruit.com>
License: MIT
Project-URL: Homepage, https://github.com/adafruit/Adafruit_CircuitPython_ICM20X
Keywords: adafruit,blinka,circuitpython,micropython,icm20649,icm20948,icm20x,gyro,accelerometer,high-G,6-axis,wide,range
Classifier: Intended Audience :: Developers
Classifier: Topic :: Software Development :: Libraries
Classifier: Topic :: Software Development :: Embedded Systems
Classifier: Topic :: System :: Hardware
Classifier: License :: OSI Approved :: MIT License
Classifier: Programming Language :: Python :: 3
License-File: LICENSE
Requires-Dist: Adafruit-Blinka
Requires-Dist: adafruit-circuitpython-register
Requires-Dist: adafruit-circuitpython-busdevice
Provides-Extra: optional
Dynamic: license-file
